crawlio/__init__.py
crawlio/client.py
crawlio/exception.py
crawlio/types.py
crawlio_py-0.1.3.dist-info/licenses/LICENSE
crawlio_py-0.1.3.dist-info/METADATA
crawlio_py-0.1.3.dist-info/WHEEL
crawlio_py-0.1.3.dist-info/top_level.txt
crawlio_py-0.1.3.dist-info/RECORD
