Metadata-Version: 2.4
Name: crawlio-py
Version: 0.1.3
Summary: Python SDK for the Crawlio web scraping API
Author-email: Kishan Sharma <kisshan07@outlook.com>
License-Expression: MIT
Project-URL: Homepage, https://crawlio.xyz
Project-URL: Documentation, https://github.com/weekend-dev-labs/crawlio-py
Project-URL: Source, https://github.com/weekend-dev-labs/crawlio-py
Requires-Python: >=3.7
License-File: LICENSE
Requires-Dist: requests
Dynamic: license-file
